hoymiles_mqtt/__init__.py
hoymiles_mqtt/__main__.py
hoymiles_mqtt/ha.py
hoymiles_mqtt/mqtt.py
hoymiles_mqtt/runners.py
hoymiles_mqtt-0.11.0.dist-info/LICENSE
hoymiles_mqtt-0.11.0.dist-info/METADATA
hoymiles_mqtt-0.11.0.dist-info/WHEEL
hoymiles_mqtt-0.11.0.dist-info/RECORD
