Metadata-Version: 2.3
Name: hoymiles-mqtt
Version: 0.11.0
Summary: Send data from Hoymiles photovoltaic installation to MQTT server.
License: MIT
Author: Mariusz Wasiluk
Requires-Python: >=3.10,<3.14
Classifier: Development Status :: 2 - Pre-Alpha
Classifier: Intended Audience :: Developers
Classifier: License :: OSI Approved :: MIT License
Classifier: Natural Language :: English
Classifier: Programming Language :: Python :: 3
Classifier: Programming Language :: Python :: 3.10
Classifier: Programming Language :: Python :: 3.11
Classifier: Programming Language :: Python :: 3.12
Classifier: Programming Language :: Python :: 3.13
Provides-Extra: dev
Provides-Extra: doc
Provides-Extra: test
Requires-Dist: ConfigArgParse (>=1.5.3,<2.0.0)
Requires-Dist: black (>=24.8.0,<25.0.0) ; extra == "test"
Requires-Dist: bump2version (>=1.0.1,<2.0.0) ; extra == "dev"
Requires-Dist: flake8 (>=7.1.1,<8.0.0) ; extra == "test"
Requires-Dist: flake8-docstrings (>=1.6.0,<2.0.0) ; extra == "test"
Requires-Dist: hoymiles-modbus (>=0.10.0,<0.11.0)
Requires-Dist: isort (>=5.8.0,<6.0.0) ; extra == "test"
Requires-Dist: mkdocs (>=1.6.0,<2.0.0) ; extra == "doc"
Requires-Dist: mkdocs-autorefs (>=0.3.1) ; extra == "doc"
Requires-Dist: mkdocs-include-markdown-plugin (>=6.0.0,<7.0.0) ; extra == "doc"
Requires-Dist: mkdocs-material (>=9.0.11,<10.0.0) ; extra == "doc"
Requires-Dist: mkdocstrings[python] (>=0.25.2,<0.26.0) ; extra == "doc"
Requires-Dist: mypy (>=1,<2) ; extra == "test"
Requires-Dist: paho-mqtt (>=2.1.0,<3.0.0)
Requires-Dist: pre-commit (>=3.8.0,<4.0.0) ; extra == "dev"
Requires-Dist: pytest (>=8.3.2,<9.0.0) ; extra == "test"
Requires-Dist: pytest-cov (>=5.0.0,<6.0.0) ; extra == "test"
Requires-Dist: toml (>=0.10.2,<0.11.0) ; extra == "dev"
Requires-Dist: tox (>=4.17.1,<5.0.0) ; extra == "dev"
Requires-Dist: twine (>=5.1.1,<6.0.0) ; extra == "dev"
Requires-Dist: virtualenv (>=20.2.2,<21.0.0) ; extra == "dev"
Project-URL: Homepage, https://github.com/wasilukm/hoymiles-mqtt
